hagerstrand/__init__.py
hagerstrand/basemaps.py
hagerstrand/common.py
hagerstrand/dataprocess.py
hagerstrand/hagerstrand.py
hagerstrand/toolbar.py
hagerstrand/utils.py
hagerstrand-0.0.11.dist-info/LICENSE
hagerstrand-0.0.11.dist-info/METADATA
hagerstrand-0.0.11.dist-info/WHEEL
hagerstrand-0.0.11.dist-info/dependency_links.txt
hagerstrand-0.0.11.dist-info/top_level.txt
hagerstrand-0.0.11.dist-info/RECORD
