Metadata-Version: 2.1
Name: hagerstrand
Version: 0.0.11
Summary: A Python package for an interactive space-time Geographic Information System (GIS)
Home-page: https://github.com/jimmy-feng/hagerstrand
Author: Jimmy Feng
Author-email: jfeng1996@gmail.com
License: MIT license
Keywords: hagerstrand
Platform: UNKNOWN
Classifier: Development Status :: 2 - Pre-Alpha
Classifier: Intended Audience :: Developers
Classifier: License :: OSI Approved :: MIT License
Classifier: Natural Language :: English
Classifier: Programming Language :: Python :: 3
Classifier: Programming Language :: Python :: 3.5
Classifier: Programming Language :: Python :: 3.6
Classifier: Programming Language :: Python :: 3.7
Classifier: Programming Language :: Python :: 3.8
Requires-Python: >=3.5
Requires-Dist: folium
Requires-Dist: ipyleaflet
Requires-Dist: ipyfilechooser
Requires-Dist: ipywidgets
Requires-Dist: pyshp
Requires-Dist: pandas
Requires-Dist: geopandas
Requires-Dist: shapely
Requires-Dist: earthengine-api
Requires-Dist: scikit-learn
Requires-Dist: python-box
Requires-Dist: ee
Requires-Dist: geemap
